automatas/__init__.py
automatas/base_automata.py
automatas/mealy_automata.py
automatas/moor_automata.py
jflap/__init__.py
jflap/to_jflap_mealy.py
jflap/to_jflap_moor.py
minimization/__init__.py
minimization/pi_minimization.py
transformations/__init__.py
transformations/from_mealy_to_moor.py
pyautomatatheory-0.0.1.dist-info/METADATA
pyautomatatheory-0.0.1.dist-info/WHEEL
pyautomatatheory-0.0.1.dist-info/top_level.txt
pyautomatatheory-0.0.1.dist-info/RECORD
